odoo10_addon_storage_image_product-10.0.2.2.1-py3.8-nspkg.pth
odoo/addons/storage_image_product/README.rst
odoo/addons/storage_image_product/__init__.py
odoo/addons/storage_image_product/__manifest__.py
odoo/addons/storage_image_product/i18n/storage_image_product.pot
odoo/addons/storage_image_product/migrations/10.0.2.0.0/pre-migration.py
odoo/addons/storage_image_product/models/__init__.py
odoo/addons/storage_image_product/models/category_image_relation.py
odoo/addons/storage_image_product/models/image_tag.py
odoo/addons/storage_image_product/models/product_category.py
odoo/addons/storage_image_product/models/product_image_relation.py
odoo/addons/storage_image_product/models/product_product.py
odoo/addons/storage_image_product/models/product_template.py
odoo/addons/storage_image_product/security/ir.model.access.csv
odoo/addons/storage_image_product/static/description/icon.png
odoo/addons/storage_image_product/tests/__init__.py
odoo/addons/storage_image_product/tests/common.py
odoo/addons/storage_image_product/tests/test_product_image_relation.py
odoo/addons/storage_image_product/tests/static/black-image.jpg
odoo/addons/storage_image_product/tests/static/logo-image.jpg
odoo/addons/storage_image_product/tests/static/white-image.jpg
odoo/addons/storage_image_product/views/image_tag.xml
odoo/addons/storage_image_product/views/product_category.xml
odoo/addons/storage_image_product/views/product_image_relation.xml
odoo/addons/storage_image_product/views/product_product.xml
odoo/addons/storage_image_product/views/product_template.xml
odoo10_addon_storage_image_product-10.0.2.2.1.dist-info/METADATA
odoo10_addon_storage_image_product-10.0.2.2.1.dist-info/WHEEL
odoo10_addon_storage_image_product-10.0.2.2.1.dist-info/namespace_packages.txt
odoo10_addon_storage_image_product-10.0.2.2.1.dist-info/top_level.txt
odoo10_addon_storage_image_product-10.0.2.2.1.dist-info/RECORD
